{"info": {"name": "external", "date_created": "03/08/2022"}, "images": {"id": 1, "width": 800, "height": 600, "file_name": "0506437_as-3199886.jpg"}, "annotations": [{"id": 2, "image_id": 1, "category_id": "as-3199886", "segmentation": [[[[465, 227], [483, 240], [481, 325], [466, 437], [419, 440], [447, 306], [465, 227]]]], "area": 7445.5, "bbox": [419, 227, 64, 213], "damage": "Breakage", "part": null, "year": 2018, "color": "Others", "level": null, "repair": ["Rear bumper:exchange"]}, {"id": 3, "image_id": 1, "category_id": "as-3199886", "segmentation": [[[[435, 147], [535, 152], [653, 198], [652, 227], [448, 206], [435, 147]]]], "area": 11073.0, "bbox": [435, 147, 218, 80], "damage": "Scratched", "part": null, "year": 2018, "color": "Others", "level": null, "repair": ["Rear bumper:exchange"]}, {"id": 4, "image_id": 1, "category_id": "as-3199886", "segmentation": [[[[87, 259], [291, 213], [356, 378], [242, 394], [169, 395], [119, 361], [63, 314], [87, 259]]]], "area": 36375.0, "bbox": [63, 213, 293, 182], "damage": "Scratched", "part": null, "year": 2018, "color": "Others", "level": null, "repair": ["Rear bumper:exchange"]}], "categories": {"id": "as-3199886", "supercategory_name": "Full-size car"}}