{"info": {"name": "socar", "date_created": "03/08/2022"}, "images": {"id": 1, "width": 800, "height": 600, "file_name": "0506495_sc-226951.jpg"}, "annotations": [{"id": 2, "image_id": 1, "category_id": "sc-226951", "segmentation": [[[[17, 279], [265, 251], [486, 241], [501, 199], [566, 193], [565, 209], [752, 210], [750, 223], [546, 249], [528, 262], [513, 312], [486, 307], [480, 287], [376, 294], [351, 342], [270, 342], [239, 285], [14, 306], [17, 279]]]], "area": 33710.5, "bbox": [14, 193, 738, 149], "damage": "Scratched", "part": null, "year": 2018, "color": "White", "level": null, "repair": ["Front bumper:coating,sheet_metal", "Rear door(R):sheet_metal,coating"]}, {"id": 3, "image_id": 1, "category_id": "sc-226951", "segmentation": [[[[494, 412], [494, 427], [486, 424], [488, 409], [494, 412]]]], "area": 108.0, "bbox": [486, 409, 8, 18], "damage": "Scratched", "part": null, "year": 2018, "color": "White", "level": null, "repair": ["Front bumper:coating,sheet_metal", "Rear door(R):sheet_metal,coating"]}], "categories": {"id": "sc-226951", "supercategory_name": "CityCar"}}