{"info": {"name": "socar", "date_created": "03/08/2022"}, "images": {"id": 1, "width": 800, "height": 600, "file_name": "0506453_sc-155167.jpg"}, "annotations": [{"id": 2, "image_id": 1, "category_id": "sc-155167", "segmentation": [[[[234, 447], [305, 314], [350, 207], [375, 115], [408, 0], [638, 0], [594, 137], [544, 261], [494, 363], [442, 419], [234, 447]]]], "area": 94299.5, "bbox": [234, 0, 404, 447], "damage": "Separated", "part": null, "year": 2016, "color": "White", "level": null, "repair": ["Head lights(R):repair", "Front bumper:repair,coating,exchange"]}], "categories": {"id": "sc-155167", "supercategory_name": "Mid-size car"}}