{"info": {"name": "external", "date_created": "03/08/2022"}, "images": {"id": 1, "width": 800, "height": 600, "file_name": "0506659_as-2749988.jpg"}, "annotations": [{"id": 2, "image_id": 1, "category_id": "as-2749988", "segmentation": [[[[575, 455], [607, 430], [621, 437], [619, 446], [617, 452], [601, 459], [593, 461], [575, 460], [575, 455]]], [[[365, 355], [371, 338], [398, 322], [234, 303], [250, 286], [405, 299], [469, 318], [506, 357], [524, 390], [514, 398], [507, 387], [482, 376], [461, 370], [416, 348], [390, 349], [365, 355]]]], "area": 10140.0, "bbox": [234, 286, 290, 112], "damage": "Scratched", "part": null, "year": 2018, "color": "Others", "level": null, "repair": ["Side mirror(R):exchange", "Front bumper:repair", "Rear Wheel(R):exchange", "Rear fender(R):exchange,coating,sheet_metal", "Rear bumper:coating,repair", "Rear door(R):exchange,coating,sheet_metal,repair", "Head lights:exchange", "Bumper:coating"]}], "categories": {"id": "as-2749988", "supercategory_name": "Full-size car"}}