{"info": {"name": "external", "date_created": "03/08/2022"}, "images": {"id": 1, "width": 800, "height": 600, "file_name": "0506464_as-2977436.jpg"}, "annotations": [{"id": 1, "image_id": 1, "category_id": "as-2977436", "segmentation": [[[[527, 195], [564, 266], [569, 277], [571, 283], [553, 287], [537, 294], [528, 302], [524, 307], [521, 286], [519, 276], [520, 268], [526, 251], [526, 234], [526, 225], [526, 210], [527, 195]]]], "area": 2652.0, "bbox": [519, 195, 52, 112], "damage": "Separated", "part": null, "year": 2013, "color": "Blue tone", "level": null, "repair": ["Front fender(L):exchange,coating", "Front bumper:coating,exchange", "Rear bumper:coating,exchange", "Rear fender(L):coating,sheet_metal,exchange", "Front door(L):coating", "Head lights:exchange", "Rear Wheel(L):exchange", "Front Wheel(L):exchange,exchange,sheet_metal", "Rear door(L):coating"]}], "categories": {"id": "as-2977436", "supercategory_name": "CityCar"}}