{"info": {"name": "external", "date_created": "03/08/2022"}, "images": {"id": 1, "width": 800, "height": 600, "file_name": "0506944_as-0045534.jpg"}, "annotations": [{"id": 2, "image_id": 1, "category_id": "as-0045534", "segmentation": [[[[373, 129], [502, 60], [594, 182], [504, 220], [373, 129]]]], "area": 17627.0, "bbox": [373, 60, 221, 160], "damage": "Scratched", "part": null, "year": 2015, "color": "Black", "level": null, "repair": ["Front door(L):exchange,coating", "Rear door(L):coating,exchange", "Rocker panel:exchange", "Rear fender(L):coating,sheet_metal"]}, {"id": 3, "image_id": 1, "category_id": "as-0045534", "segmentation": [[[[235, 136], [622, 249], [561, 410], [345, 336], [361, 282], [239, 179], [244, 145], [235, 136]]]], "area": 49801.5, "bbox": [235, 136, 387, 274], "damage": "Breakage", "part": null, "year": 2015, "color": "Black", "level": null, "repair": ["Front door(L):exchange,coating", "Rear door(L):coating,exchange", "Rocker panel:exchange", "Rear fender(L):coating,sheet_metal"]}], "categories": {"id": "as-0045534", "supercategory_name": "Full-size car"}}