{"info": {"name": "socar", "date_created": "03/08/2022"}, "images": {"id": 1, "width": 800, "height": 600, "file_name": "0506856_sc-213030.jpg"}, "annotations": [{"id": 2, "image_id": 1, "category_id": "sc-213030", "segmentation": [[[[2, 85], [357, 148], [419, 143], [476, 73], [484, 94], [436, 151], [375, 187], [294, 194], [237, 194], [230, 177], [5, 139], [2, 85]]]], "area": 22659.5, "bbox": [2, 73, 482, 121], "damage": "Scratched", "part": null, "year": 2018, "color": "White", "level": null, "repair": []}, {"id": 3, "image_id": 1, "category_id": "sc-213030", "segmentation": [[[[467, 174], [515, 135], [549, 128], [582, 137], [609, 164], [625, 208], [610, 242], [599, 233], [600, 211], [591, 182], [574, 158], [515, 153], [477, 183], [467, 174]]]], "area": 4468.5, "bbox": [467, 128, 158, 114], "damage": "Scratched", "part": null, "year": 2018, "color": "White", "level": null, "repair": []}, {"id": 4, "image_id": 1, "category_id": "sc-213030", "segmentation": [[[[434, 289], [463, 348], [506, 354], [510, 364], [563, 394], [553, 406], [516, 407], [454, 403], [406, 390], [375, 369], [365, 359], [413, 338], [434, 289]]]], "area": 9423.0, "bbox": [365, 289, 198, 118], "damage": "Scratched", "part": null, "year": 2018, "color": "White", "level": null, "repair": []}, {"id": 5, "image_id": 1, "category_id": "sc-213030", "segmentation": [[[[583, 174], [594, 196], [585, 239], [567, 302], [540, 343], [523, 353], [489, 353], [465, 339], [456, 327], [453, 302], [456, 269], [462, 234], [468, 224], [468, 238], [463, 270], [460, 297], [461, 317], [466, 330], [475, 340], [496, 346], [518, 347], [536, 338], [551, 325], [568, 293], [577, 254], [590, 213], [590, 193], [583, 174]]]], "area": 1674.0, "bbox": [453, 174, 141, 179], "damage": "Separated", "part": null, "year": 2018, "color": "White", "level": null, "repair": []}], "categories": {"id": "sc-213030", "supercategory_name": "CityCar"}}