{"info": {"name": "external", "date_created": "03/08/2022"}, "images": {"id": 1, "width": 800, "height": 600, "file_name": "0506784_as-9039802.jpg"}, "annotations": [{"id": 1, "image_id": 1, "category_id": "as-9039802", "segmentation": [[[[4, 537], [2, 461], [215, 386], [266, 341], [534, 225], [542, 234], [503, 257], [282, 349], [250, 394], [373, 352], [453, 321], [596, 265], [602, 272], [430, 347], [308, 417], [200, 469], [4, 537]]]], "area": 32960.5, "bbox": [2, 225, 600, 312], "damage": "Scratched", "part": null, "year": 2012, "color": "Blue tone", "level": null, "repair": ["Front door(R):sheet_metal,coating", "Rear bumper:coating,repair", "Rocker panel:sheet_metal,coating", "Rear door(R):coating,sheet_metal", "Front fender(R):sheet_metal,coating", "Front bumper:repair,coating", "Rear fender(R):coating,sheet_metal"]}], "categories": {"id": "as-9039802", "supercategory_name": "Full-size car"}}