{"info": {"name": "socar", "date_created": "03/08/2022"}, "images": {"id": 1, "width": 960, "height": 720, "file_name": "0507460_sc-227088.jpg"}, "annotations": [{"id": 2, "image_id": 1, "category_id": "sc-227088", "segmentation": [[[[835, 175], [846, 193], [714, 224], [631, 187], [612, 177], [652, 172], [706, 201], [835, 175]]]], "area": 4709.5, "bbox": [612, 172, 234, 52], "damage": "Scratched", "part": null, "year": 2020, "color": "White", "level": null, "repair": ["Rear door(R):sheet_metal,coating"]}, {"id": 3, "image_id": 1, "category_id": "sc-227088", "segmentation": [[[[299, 178], [318, 155], [359, 164], [403, 167], [334, 190], [337, 242], [374, 249], [459, 253], [535, 200], [555, 191], [565, 198], [589, 198], [637, 239], [668, 268], [691, 277], [647, 296], [718, 313], [785, 296], [810, 314], [834, 324], [792, 333], [792, 319], [706, 357], [707, 404], [959, 335], [960, 373], [907, 404], [608, 505], [333, 620], [333, 541], [447, 490], [474, 386], [463, 344], [404, 348], [390, 321], [343, 314], [299, 178]]]], "area": 111589.5, "bbox": [299, 155, 661, 465], "damage": "Scratched", "part": null, "year": 2020, "color": "White", "level": null, "repair": ["Rear door(R):sheet_metal,coating"]}, {"id": 4, "image_id": 1, "category_id": "sc-227088", "segmentation": [[[[426, 5], [437, 1], [541, 180], [648, 294], [721, 306], [726, 315], [663, 312], [605, 288], [484, 113], [426, 5]]]], "area": 6576.5, "bbox": [426, 1, 300, 314], "damage": "Separated", "part": null, "year": 2020, "color": "White", "level": null, "repair": ["Rear door(R):sheet_metal,coating"]}, {"id": 5, "image_id": 1, "category_id": "sc-227088", "segmentation": [[[[350, 320], [318, 258], [468, 243], [561, 252], [585, 306], [573, 346], [540, 320], [485, 323], [350, 320]]]], "area": 17945.5, "bbox": [318, 243, 267, 103], "damage": "Crushed", "part": null, "year": 2020, "color": "White", "level": null, "repair": ["Rear door(R):sheet_metal,coating"]}, {"id": 6, "image_id": 1, "category_id": "sc-227088", "segmentation": [[[[694, 426], [721, 401], [740, 448], [648, 479], [333, 609], [334, 575], [346, 553], [373, 539], [459, 489], [563, 449], [694, 426]]]], "area": 22377.5, "bbox": [333, 401, 407, 208], "damage": "Crushed", "part": null, "year": 2020, "color": "White", "level": null, "repair": ["Rear door(R):sheet_metal,coating"]}], "categories": {"id": "sc-227088", "supercategory_name": "Mid-size car"}}