{"info": {"name": "external", "date_created": "03/08/2022"}, "images": {"id": 1, "width": 800, "height": 600, "file_name": "0507880_as-0031052.jpg"}, "annotations": [{"id": 2, "image_id": 1, "category_id": "as-0031052", "segmentation": [[[[84, 186], [240, 155], [538, 96], [753, 111], [779, 172], [778, 215], [519, 324], [287, 401], [133, 406], [117, 379], [84, 186]]]], "area": 141907.0, "bbox": [84, 96, 695, 310], "damage": "Scratched", "part": null, "year": 2015, "color": "Black", "level": null, "repair": ["Rear door(R):exchange,coating,sheet_metal", "Front door(R):sheet_metal,coating,exchange"]}], "categories": {"id": "as-0031052", "supercategory_name": "Full-size car"}}