{"info": {"name": "socar", "date_created": "03/08/2022"}, "images": {"id": 1, "width": 960, "height": 720, "file_name": "0507160_sc-219275.jpg"}, "annotations": [{"id": 2, "image_id": 1, "category_id": "sc-219275", "segmentation": [[[[494, 171], [622, 174], [666, 227], [656, 237], [542, 226], [503, 194], [494, 171]]]], "area": 7641.5, "bbox": [494, 171, 172, 66], "damage": "Scratched", "part": null, "year": 2017, "color": "White", "level": null, "repair": ["Front bumper:repair,coating,exchange"]}], "categories": {"id": "sc-219275", "supercategory_name": "Compact car"}}