{"info": {"name": "socar", "date_created": "03/08/2022"}, "images": {"id": 1, "width": 800, "height": 600, "file_name": "0507434_sc-194890.jpg"}, "annotations": [{"id": 2, "image_id": 1, "category_id": "sc-194890", "segmentation": [[[[190, 149], [207, 136], [221, 129], [226, 135], [239, 140], [240, 149], [249, 165], [255, 179], [283, 182], [326, 192], [381, 207], [420, 219], [421, 228], [381, 216], [324, 204], [274, 192], [247, 190], [240, 195], [222, 219], [215, 228], [210, 238], [207, 245], [214, 244], [211, 254], [200, 264], [196, 269], [187, 277], [182, 279], [181, 264], [176, 261], [166, 251], [160, 242], [160, 237], [177, 244], [188, 245], [193, 234], [199, 222], [206, 212], [212, 203], [215, 195], [215, 188], [203, 184], [199, 177], [190, 149]]]], "area": 6659.0, "bbox": [160, 129, 261, 150], "damage": "Scratched", "part": null, "year": 2017, "color": "White", "level": null, "repair": ["Front bumper:coating,sheet_metal,exchange", "Rear door(R):sheet_metal,exchange,coating"]}, {"id": 3, "image_id": 1, "category_id": "sc-194890", "segmentation": [[[[436, 45], [434, 53], [413, 50], [359, 45], [320, 42], [297, 46], [282, 57], [259, 65], [236, 78], [214, 83], [191, 89], [168, 90], [160, 84], [157, 78], [174, 77], [191, 72], [192, 68], [183, 63], [183, 59], [184, 51], [195, 52], [207, 52], [214, 39], [227, 38], [254, 29], [271, 25], [436, 45]]]], "area": 5752.0, "bbox": [157, 25, 279, 65], "damage": "Scratched", "part": null, "year": 2017, "color": "White", "level": null, "repair": ["Front bumper:coating,sheet_metal,exchange", "Rear door(R):sheet_metal,exchange,coating"]}, {"id": 4, "image_id": 1, "category_id": "sc-194890", "segmentation": [[[[466, 232], [564, 259], [558, 268], [543, 265], [521, 258], [502, 251], [460, 238], [466, 232]]]], "area": 967.0, "bbox": [460, 232, 104, 36], "damage": "Scratched", "part": null, "year": 2017, "color": "White", "level": null, "repair": ["Front bumper:coating,sheet_metal,exchange", "Rear door(R):sheet_metal,exchange,coating"]}, {"id": 5, "image_id": 1, "category_id": "sc-194890", "segmentation": [[[[619, 318], [634, 317], [635, 325], [621, 325], [619, 318]]]], "area": 109.5, "bbox": [619, 317, 16, 8], "damage": "Scratched", "part": null, "year": 2017, "color": "White", "level": null, "repair": ["Front bumper:coating,sheet_metal,exchange", "Rear door(R):sheet_metal,exchange,coating"]}, {"id": 6, "image_id": 1, "category_id": "sc-194890", "segmentation": [[[[294, 338], [449, 370], [526, 382], [579, 386], [620, 387], [627, 388], [630, 395], [625, 397], [593, 395], [519, 387], [452, 380], [370, 363], [311, 349], [291, 341], [294, 338]]]], "area": 2721.5, "bbox": [291, 338, 339, 59], "damage": "Scratched", "part": null, "year": 2017, "color": "White", "level": null, "repair": ["Front bumper:coating,sheet_metal,exchange", "Rear door(R):sheet_metal,exchange,coating"]}, {"id": 7, "image_id": 1, "category_id": "sc-194890", "segmentation": [[[[181, 294], [188, 292], [193, 299], [200, 313], [204, 320], [211, 314], [214, 316], [216, 320], [224, 320], [230, 332], [222, 332], [213, 334], [223, 349], [235, 368], [244, 378], [250, 380], [259, 390], [266, 399], [274, 406], [281, 411], [298, 420], [307, 422], [315, 431], [308, 431], [295, 428], [290, 422], [275, 418], [259, 415], [254, 411], [259, 409], [248, 399], [239, 388], [227, 373], [215, 357], [207, 342], [204, 335], [198, 327], [197, 321], [181, 294]]]], "area": 2159.5, "bbox": [181, 292, 134, 139], "damage": "Scratched", "part": null, "year": 2017, "color": "White", "level": null, "repair": ["Front bumper:coating,sheet_metal,exchange", "Rear door(R):sheet_metal,exchange,coating"]}, {"id": 8, "image_id": 1, "category_id": "sc-194890", "segmentation": [[[[170, 330], [189, 328], [191, 335], [187, 337], [172, 340], [170, 330]]]], "area": 177.5, "bbox": [170, 328, 21, 12], "damage": "Scratched", "part": null, "year": 2017, "color": "White", "level": null, "repair": ["Front bumper:coating,sheet_metal,exchange", "Rear door(R):sheet_metal,exchange,coating"]}, {"id": 9, "image_id": 1, "category_id": "sc-194890", "segmentation": [[[[188, 390], [196, 387], [201, 396], [214, 410], [225, 419], [240, 429], [247, 432], [253, 426], [261, 428], [258, 436], [266, 433], [273, 425], [278, 431], [276, 438], [276, 442], [271, 443], [274, 452], [258, 446], [239, 434], [224, 426], [209, 418], [196, 407], [188, 390]]]], "area": 1063.0, "bbox": [188, 387, 90, 65], "damage": "Scratched", "part": null, "year": 2017, "color": "White", "level": null, "repair": ["Front bumper:coating,sheet_metal,exchange", "Rear door(R):sheet_metal,exchange,coating"]}, {"id": 10, "image_id": 1, "category_id": "sc-194890", "segmentation": [[[[320, 425], [527, 457], [535, 458], [533, 466], [492, 461], [432, 453], [394, 446], [392, 452], [357, 444], [357, 438], [321, 430], [320, 425]]]], "area": 2111.0, "bbox": [320, 425, 215, 41], "damage": "Scratched", "part": null, "year": 2017, "color": "White", "level": null, "repair": ["Front bumper:coating,sheet_metal,exchange", "Rear door(R):sheet_metal,exchange,coating"]}, {"id": 11, "image_id": 1, "category_id": "sc-194890", "segmentation": [[[[354, 410], [362, 414], [362, 420], [352, 415], [354, 410]]]], "area": 54.0, "bbox": [352, 410, 10, 10], "damage": "Scratched", "part": null, "year": 2017, "color": "White", "level": null, "repair": ["Front bumper:coating,sheet_metal,exchange", "Rear door(R):sheet_metal,exchange,coating"]}, {"id": 12, "image_id": 1, "category_id": "sc-194890", "segmentation": [[[[352, 471], [359, 456], [364, 457], [362, 465], [361, 474], [352, 471]]]], "area": 117.0, "bbox": [352, 456, 12, 18], "damage": "Breakage", "part": null, "year": 2017, "color": "White", "level": null, "repair": ["Front bumper:coating,sheet_metal,exchange", "Rear door(R):sheet_metal,exchange,coating"]}, {"id": 13, "image_id": 1, "category_id": "sc-194890", "segmentation": [[[[470, 550], [539, 520], [536, 529], [518, 537], [496, 550], [479, 557], [470, 550]]]], "area": 600.5, "bbox": [470, 520, 69, 37], "damage": "Scratched", "part": null, "year": 2017, "color": "White", "level": null, "repair": ["Front bumper:coating,sheet_metal,exchange", "Rear door(R):sheet_metal,exchange,coating"]}, {"id": 14, "image_id": 1, "category_id": "sc-194890", "segmentation": [[[[486, 494], [532, 496], [532, 499], [531, 510], [524, 515], [506, 526], [506, 523], [511, 511], [510, 502], [505, 501], [484, 497], [486, 494]]]], "area": 608.0, "bbox": [484, 494, 48, 32], "damage": "Scratched", "part": null, "year": 2017, "color": "White", "level": null, "repair": ["Front bumper:coating,sheet_metal,exchange", "Rear door(R):sheet_metal,exchange,coating"]}], "categories": {"id": "sc-194890", "supercategory_name": "Mid-size car"}}