{"info": {"name": "external", "date_created": "03/08/2022"}, "images": {"id": 1, "width": 800, "height": 600, "file_name": "0507983_as-0012711.jpg"}, "annotations": [{"id": 2, "image_id": 1, "category_id": "as-0012711", "segmentation": [[[[464, 330], [498, 321], [566, 305], [565, 314], [509, 328], [478, 333], [473, 333], [464, 330]]]], "area": 828.5, "bbox": [464, 305, 102, 28], "damage": "Scratched", "part": null, "year": 2017, "color": "Gray tone", "level": null, "repair": ["Front bumper:repair,coating", "Rear door(R):exchange,coating,sheet_metal", "Front door(R):sheet_metal,coating,exchange", "Rear bumper:coating,exchange", "Rear fender(R):coating,sheet_metal", "Front fender(R):sheet_metal,coating"]}, {"id": 3, "image_id": 1, "category_id": "as-0012711", "segmentation": [[[[175, 1], [373, 1], [478, 32], [580, 72], [703, 107], [705, 126], [622, 109], [435, 63], [300, 37], [175, 1]]]], "area": 16483.5, "bbox": [175, 1, 530, 125], "damage": "Scratched", "part": null, "year": 2017, "color": "Gray tone", "level": null, "repair": ["Front bumper:repair,coating", "Rear door(R):exchange,coating,sheet_metal", "Front door(R):sheet_metal,coating,exchange", "Rear bumper:coating,exchange", "Rear fender(R):coating,sheet_metal", "Front fender(R):sheet_metal,coating"]}, {"id": 4, "image_id": 1, "category_id": "as-0012711", "segmentation": [[[[0, 286], [294, 261], [294, 271], [0, 304], [0, 286]]]], "area": 4116.0, "bbox": [0, 261, 294, 43], "damage": "Scratched", "part": null, "year": 2017, "color": "Gray tone", "level": null, "repair": ["Front bumper:repair,coating", "Rear door(R):exchange,coating,sheet_metal", "Front door(R):sheet_metal,coating,exchange", "Rear bumper:coating,exchange", "Rear fender(R):coating,sheet_metal", "Front fender(R):sheet_metal,coating"]}], "categories": {"id": "as-0012711", "supercategory_name": "Full-size car"}}