{"info": {"name": "socar", "date_created": "03/08/2022"}, "images": {"id": 1, "width": 1280, "height": 622, "file_name": "0508381_sc-195570.jpg"}, "annotations": [{"id": 2, "image_id": 1, "category_id": "sc-195570", "segmentation": [[[[627, 403], [626, 419], [539, 416], [455, 428], [418, 437], [450, 458], [472, 451], [488, 449], [650, 459], [653, 470], [462, 471], [397, 434], [459, 406], [464, 400], [531, 399], [627, 403]]]], "area": 7684.0, "bbox": [397, 399, 256, 72], "damage": "Scratched", "part": null, "year": 2016, "color": "White", "level": null, "repair": ["Rear door(R):sheet_metal,coating"]}, {"id": 3, "image_id": 1, "category_id": "sc-195570", "segmentation": [[[[894, 557], [882, 568], [814, 568], [661, 564], [645, 557], [647, 546], [718, 548], [894, 557]]]], "area": 3760.0, "bbox": [645, 546, 249, 22], "damage": "Scratched", "part": null, "year": 2016, "color": "White", "level": null, "repair": ["Rear door(R):sheet_metal,coating"]}, {"id": 4, "image_id": 1, "category_id": "sc-195570", "segmentation": [[[[1277, 550], [1279, 562], [1271, 562], [1263, 573], [1259, 576], [1139, 576], [1146, 565], [1231, 558], [1234, 553], [1277, 550]]]], "area": 2240.0, "bbox": [1139, 550, 140, 26], "damage": "Scratched", "part": null, "year": 2016, "color": "White", "level": null, "repair": ["Rear door(R):sheet_metal,coating"]}], "categories": {"id": "sc-195570", "supercategory_name": "Full-size car"}}