{"info": {"name": "external", "date_created": "03/08/2022"}, "images": {"id": 1, "width": 800, "height": 600, "file_name": "0508660_as-0026676.jpg"}, "annotations": [{"id": 2, "image_id": 1, "category_id": "as-0026676", "segmentation": [[[[203, 203], [230, 230], [268, 244], [329, 259], [412, 281], [383, 279], [282, 259], [262, 264], [238, 263], [223, 257], [206, 247], [234, 246], [211, 227], [195, 212], [203, 203]]]], "area": 2813.5, "bbox": [195, 203, 217, 78], "damage": "Scratched", "part": null, "year": 2017, "color": "White", "level": null, "repair": ["Front bumper:coating,exchange", "Head lights:exchange"]}, {"id": 3, "image_id": 1, "category_id": "as-0026676", "segmentation": [[[[568, 306], [580, 319], [595, 305], [590, 331], [597, 363], [633, 445], [612, 408], [596, 370], [579, 360], [571, 383], [563, 411], [541, 425], [524, 404], [551, 396], [557, 377], [570, 341], [558, 328], [537, 336], [501, 337], [483, 323], [472, 332], [466, 316], [495, 312], [512, 310], [476, 303], [463, 291], [514, 299], [568, 306]]]], "area": 5885.5, "bbox": [463, 291, 170, 154], "damage": "Scratched", "part": null, "year": 2017, "color": "White", "level": null, "repair": ["Front bumper:coating,exchange", "Head lights:exchange"]}, {"id": 4, "image_id": 1, "category_id": "as-0026676", "segmentation": [[[[294, 467], [266, 463], [271, 450], [293, 445], [310, 461], [294, 467]]]], "area": 615.5, "bbox": [266, 445, 44, 22], "damage": "Scratched", "part": null, "year": 2017, "color": "White", "level": null, "repair": ["Front bumper:coating,exchange", "Head lights:exchange"]}, {"id": 5, "image_id": 1, "category_id": "as-0026676", "segmentation": [[[[402, 484], [379, 476], [362, 459], [378, 456], [413, 475], [402, 484]]]], "area": 649.5, "bbox": [362, 456, 51, 28], "damage": "Scratched", "part": null, "year": 2017, "color": "White", "level": null, "repair": ["Front bumper:coating,exchange", "Head lights:exchange"]}, {"id": 6, "image_id": 1, "category_id": "as-0026676", "segmentation": [[[[455, 408], [469, 409], [488, 420], [499, 449], [511, 463], [514, 481], [492, 465], [486, 442], [455, 408]]]], "area": 1040.0, "bbox": [455, 408, 59, 73], "damage": "Scratched", "part": null, "year": 2017, "color": "White", "level": null, "repair": ["Front bumper:coating,exchange", "Head lights:exchange"]}, {"id": 7, "image_id": 1, "category_id": "as-0026676", "segmentation": [[[[292, 389], [304, 397], [312, 391], [323, 391], [327, 393], [332, 390], [347, 393], [358, 393], [367, 395], [376, 398], [386, 397], [400, 398], [417, 397], [444, 404], [469, 428], [472, 446], [435, 449], [402, 446], [350, 438], [315, 435], [277, 429], [261, 418], [252, 404], [264, 396], [276, 393], [292, 389]]]], "area": 8861.0, "bbox": [252, 389, 220, 60], "damage": "Scratched", "part": null, "year": 2017, "color": "White", "level": null, "repair": ["Front bumper:coating,exchange", "Head lights:exchange"]}, {"id": 8, "image_id": 1, "category_id": "as-0026676", "segmentation": [[[[214, 344], [212, 364], [213, 376], [212, 387], [207, 400], [204, 420], [193, 417], [184, 407], [176, 394], [174, 386], [186, 395], [196, 410], [202, 401], [203, 385], [202, 375], [199, 365], [194, 354], [190, 346], [204, 349], [211, 352], [209, 333], [209, 324], [215, 323], [216, 333], [214, 344]]]], "area": 1137.5, "bbox": [174, 323, 42, 97], "damage": "Scratched", "part": null, "year": 2017, "color": "White", "level": null, "repair": ["Front bumper:coating,exchange", "Head lights:exchange"]}], "categories": {"id": "as-0026676", "supercategory_name": "Mid-size car"}}