{"info": {"name": "external", "date_created": "03/08/2022"}, "images": {"id": 1, "width": 800, "height": 600, "file_name": "0508330_as-2705990.jpg"}, "annotations": [{"id": 2, "image_id": 1, "category_id": "as-2705990", "segmentation": [[[[432, 343], [444, 362], [438, 393], [432, 372], [432, 343]]]], "area": 330.0, "bbox": [432, 343, 12, 50], "damage": "Scratched", "part": null, "year": 2019, "color": "Others", "level": null, "repair": ["Bumper:coating,exchange", "Rocker panel:exchange"]}, {"id": 3, "image_id": 1, "category_id": "as-2705990", "segmentation": [[[[430, 0], [449, 0], [446, 103], [444, 398], [441, 599], [425, 600], [423, 424], [430, 0]]]], "area": 11283.0, "bbox": [423, 0, 26, 600], "damage": "Separated", "part": null, "year": 2019, "color": "Others", "level": null, "repair": ["Bumper:coating,exchange", "Rocker panel:exchange"]}], "categories": {"id": "as-2705990", "supercategory_name": "Mid-size car"}}