{"info": {"name": "socar", "date_created": "03/08/2022"}, "images": {"id": 1, "width": 800, "height": 600, "file_name": "0508217_sc-1013406.jpg"}, "annotations": [{"id": 2, "image_id": 1, "category_id": "sc-1013406", "segmentation": [[[[478, 0], [791, 46], [780, 86], [418, 11], [478, 0]]]], "area": 10754.0, "bbox": [418, 0, 373, 86], "damage": "Separated", "part": null, "year": 2017, "color": "White", "level": null, "repair": ["Front bumper:coating,exchange"]}, {"id": 3, "image_id": 1, "category_id": "sc-1013406", "segmentation": [[[[175, 11], [266, 0], [292, 66], [175, 11]]]], "area": 3146.0, "bbox": [175, 0, 117, 66], "damage": "Scratched", "part": null, "year": 2017, "color": "White", "level": null, "repair": ["Front bumper:coating,exchange"]}, {"id": 4, "image_id": 1, "category_id": "sc-1013406", "segmentation": [[[[177, 102], [317, 167], [381, 249], [257, 216], [177, 102]]]], "area": 9408.0, "bbox": [177, 102, 204, 147], "damage": "Scratched", "part": null, "year": 2017, "color": "White", "level": null, "repair": ["Front bumper:coating,exchange"]}, {"id": 5, "image_id": 1, "category_id": "sc-1013406", "segmentation": [[[[26, 145], [394, 272], [699, 334], [714, 365], [656, 424], [245, 491], [206, 493], [0, 329], [26, 145]]]], "area": 134220.0, "bbox": [0, 145, 714, 348], "damage": "Breakage", "part": null, "year": 2017, "color": "White", "level": null, "repair": ["Front bumper:coating,exchange"]}, {"id": 6, "image_id": 1, "category_id": "sc-1013406", "segmentation": [[[[27, 393], [155, 421], [219, 397], [247, 396], [239, 509], [258, 512], [245, 526], [198, 563], [4, 484], [88, 475], [27, 393]]]], "area": 24640.0, "bbox": [4, 393, 254, 170], "damage": "Scratched", "part": null, "year": 2017, "color": "White", "level": null, "repair": ["Front bumper:coating,exchange"]}, {"id": 7, "image_id": 1, "category_id": "sc-1013406", "segmentation": [[[[335, 477], [360, 481], [360, 487], [334, 490], [335, 477]]]], "area": 242.5, "bbox": [334, 477, 26, 13], "damage": "Scratched", "part": null, "year": 2017, "color": "White", "level": null, "repair": ["Front bumper:coating,exchange"]}, {"id": 8, "image_id": 1, "category_id": "sc-1013406", "segmentation": [[[[502, 447], [647, 415], [658, 427], [508, 459], [502, 447]]]], "area": 2042.0, "bbox": [502, 415, 156, 44], "damage": "Scratched", "part": null, "year": 2017, "color": "White", "level": null, "repair": ["Front bumper:coating,exchange"]}, {"id": 9, "image_id": 1, "category_id": "sc-1013406", "segmentation": [[[[748, 319], [767, 324], [767, 344], [735, 389], [725, 392], [748, 319]]]], "area": 1348.0, "bbox": [725, 319, 42, 73], "damage": "Separated", "part": null, "year": 2017, "color": "White", "level": null, "repair": ["Front bumper:coating,exchange"]}], "categories": {"id": "sc-1013406", "supercategory_name": "Compact car"}}