{"info": {"name": "socar", "date_created": "03/08/2022"}, "images": {"id": 1, "width": 1067, "height": 600, "file_name": "0508184_sc-107666.jpg"}, "annotations": [{"id": 2, "image_id": 1, "category_id": "sc-107666", "segmentation": [[[[435, 280], [513, 273], [612, 270], [722, 274], [816, 302], [838, 319], [700, 330], [531, 326], [457, 314], [435, 280]]]], "area": 18158.5, "bbox": [435, 270, 403, 60], "damage": "Scratched", "part": null, "year": 2016, "color": "White", "level": null, "repair": ["Front bumper:coating,repair"]}, {"id": 3, "image_id": 1, "category_id": "sc-107666", "segmentation": [[[[757, 328], [951, 320], [927, 332], [877, 333], [811, 337], [757, 328]]]], "area": 1658.0, "bbox": [757, 320, 194, 17], "damage": "Separated", "part": null, "year": 2016, "color": "White", "level": null, "repair": ["Front bumper:coating,repair"]}, {"id": 4, "image_id": 1, "category_id": "sc-107666", "segmentation": [[[[70, 219], [78, 226], [73, 238], [64, 231], [70, 219]]]], "area": 140.5, "bbox": [64, 219, 14, 19], "damage": "Scratched", "part": null, "year": 2016, "color": "White", "level": null, "repair": ["Front bumper:coating,repair"]}], "categories": {"id": "sc-107666", "supercategory_name": "Mid-size car"}}