{"info": {"name": "external", "date_created": "03/08/2022"}, "images": {"id": 1, "width": 800, "height": 600, "file_name": "0508267_as-0057616.jpg"}, "annotations": [{"id": 2, "image_id": 1, "category_id": "as-0057616", "segmentation": [[[[355, 282], [466, 268], [469, 275], [472, 278], [478, 300], [469, 318], [413, 321], [395, 330], [375, 311], [355, 282]]]], "area": 4969.0, "bbox": [355, 268, 123, 62], "damage": "Crushed", "part": null, "year": 2015, "color": "White", "level": null, "repair": ["Rocker panel:exchange"]}, {"id": 3, "image_id": 1, "category_id": "as-0057616", "segmentation": [[[[373, 274], [384, 266], [389, 266], [399, 276], [386, 283], [379, 286], [373, 274]]]], "area": 295.0, "bbox": [373, 266, 26, 20], "damage": "Scratched", "part": null, "year": 2015, "color": "White", "level": null, "repair": ["Rocker panel:exchange"]}, {"id": 4, "image_id": 1, "category_id": "as-0057616", "segmentation": [[[[442, 258], [533, 226], [581, 230], [590, 246], [575, 271], [566, 292], [574, 418], [532, 423], [519, 317], [510, 285], [480, 293], [384, 294], [380, 272], [442, 258]]]], "area": 15191.0, "bbox": [380, 226, 210, 197], "damage": "Breakage", "part": null, "year": 2015, "color": "White", "level": null, "repair": ["Rocker panel:exchange"]}, {"id": 5, "image_id": 1, "category_id": "as-0057616", "segmentation": [[[[617, 26], [690, 0], [703, 0], [719, 1], [725, 23], [721, 29], [667, 38], [617, 26]]]], "area": 2484.0, "bbox": [617, 0, 108, 38], "damage": "Scratched", "part": null, "year": 2015, "color": "White", "level": null, "repair": ["Rocker panel:exchange"]}], "categories": {"id": "as-0057616", "supercategory_name": "Full-size car"}}