{"info": {"name": "socar", "date_created": "03/08/2022"}, "images": {"id": 1, "width": 800, "height": 600, "file_name": "0000835_sc-172537.jpg"}, "annotations": [{"id": 2, "image_id": 1, "category_id": "sc-172537", "segmentation": [[[[575, 298], [578, 305], [571, 310], [524, 331], [499, 337], [492, 329], [575, 298]]]], "area": 972.0, "bbox": [492, 298, 86, 39], "damage": "Separated", "part": null, "year": 2019, "color": "White", "level": null, "repair": ["Front bumper:coating,exchange"]}, {"id": 3, "image_id": 1, "category_id": "sc-172537", "segmentation": [[[[578, 240], [592, 250], [594, 259], [578, 251], [578, 240]]]], "area": 141.0, "bbox": [578, 240, 16, 19], "damage": "Separated", "part": null, "year": 2019, "color": "White", "level": null, "repair": ["Front bumper:coating,exchange"]}, {"id": 4, "image_id": 1, "category_id": "sc-172537", "segmentation": [[[[502, 292], [500, 299], [457, 296], [402, 293], [339, 293], [293, 294], [259, 299], [258, 293], [323, 290], [400, 287], [502, 292]]]], "area": 1227.0, "bbox": [258, 287, 244, 12], "damage": "Separated", "part": null, "year": 2019, "color": "White", "level": null, "repair": ["Front bumper:coating,exchange"]}, {"id": 5, "image_id": 1, "category_id": "sc-172537", "segmentation": [[[[445, 334], [450, 333], [450, 338], [444, 340], [445, 334]]]], "area": 29.5, "bbox": [444, 333, 6, 7], "damage": "Separated", "part": null, "year": 2019, "color": "White", "level": null, "repair": ["Front bumper:coating,exchange"]}, {"id": 8, "image_id": 1, "category_id": "sc-172537", "segmentation": [[[[579, 246], [597, 258], [596, 299], [592, 351], [592, 388], [590, 413], [586, 425], [565, 441], [545, 458], [534, 463], [502, 459], [494, 458], [470, 463], [402, 464], [354, 462], [306, 456], [275, 453], [256, 446], [241, 447], [230, 431], [221, 405], [214, 364], [209, 335], [208, 319], [210, 300], [214, 284], [214, 300], [219, 310], [236, 321], [251, 328], [274, 332], [293, 336], [293, 332], [274, 314], [256, 297], [279, 295], [335, 292], [390, 292], [453, 294], [503, 298], [475, 316], [453, 331], [448, 334], [447, 338], [481, 335], [514, 328], [537, 321], [562, 310], [578, 302], [582, 295], [582, 265], [579, 246]]]], "area": 56849.0, "bbox": [208, 246, 389, 218], "damage": null, "part": "Front bumper", "year": 2019, "color": "White", "level": 4, "repair": "Front bumper:coating,exchange"}], "categories": {"id": "sc-172537", "supercategory_name": "Mid-size car"}}