{"info": {"name": "external", "date_created": "03/08/2022"}, "images": {"id": 1, "width": 800, "height": 600, "file_name": "0001533_as-0077824.jpg"}, "annotations": [{"id": 2, "image_id": 1, "category_id": "as-0077824", "segmentation": [[[[283, 340], [307, 292], [353, 285], [391, 294], [410, 311], [427, 336], [441, 364], [450, 398], [452, 445], [406, 428], [358, 419], [315, 424], [303, 380], [283, 340]]]], "area": 18280.5, "bbox": [283, 285, 169, 160], "damage": "Crushed", "part": null, "year": 2016, "color": "Black", "level": null, "repair": ["Rear bumper:coating,exchange,repair", "Rear fender(L):coating,sheet_metal"]}, {"id": 3, "image_id": 1, "category_id": "as-0077824", "segmentation": [[[[253, 301], [277, 298], [308, 309], [324, 322], [324, 331], [335, 345], [307, 342], [322, 351], [325, 358], [337, 361], [348, 354], [368, 343], [381, 343], [384, 359], [387, 378], [380, 390], [386, 411], [364, 415], [367, 443], [355, 440], [347, 417], [332, 413], [325, 434], [317, 425], [300, 373], [282, 339], [261, 310], [253, 301]]]], "area": 8045.5, "bbox": [253, 298, 134, 145], "damage": "Scratched", "part": null, "year": 2016, "color": "Black", "level": null, "repair": ["Rear bumper:coating,exchange,repair", "Rear fender(L):coating,sheet_metal"]}, {"id": 4, "image_id": 1, "category_id": "as-0077824", "segmentation": [[[[330, 481], [444, 520], [442, 526], [328, 491], [330, 481]]]], "area": 986.0, "bbox": [328, 481, 116, 45], "damage": "Scratched", "part": null, "year": 2016, "color": "Black", "level": null, "repair": ["Rear bumper:coating,exchange,repair", "Rear fender(L):coating,sheet_metal"]}, {"id": 9, "image_id": 1, "category_id": "as-0077824", "segmentation": [[[[289, 355], [347, 364], [355, 358], [388, 295], [401, 273], [421, 283], [448, 286], [490, 284], [495, 300], [513, 324], [528, 338], [548, 332], [628, 295], [663, 271], [685, 253], [691, 241], [695, 230], [687, 199], [693, 215], [708, 258], [702, 311], [705, 325], [698, 348], [698, 354], [687, 382], [683, 382], [664, 402], [621, 443], [589, 465], [558, 485], [496, 514], [463, 523], [428, 520], [369, 501], [329, 490], [323, 462], [314, 417], [302, 386], [289, 355]]]], "area": 67866.0, "bbox": [289, 199, 419, 324], "damage": null, "part": "Rear bumper", "year": 2016, "color": "Black", "level": 4, "repair": ["Rear bumper:coating,exchange,repair", "Rear fender(L):coating,sheet_metal"]}, {"id": 10, "image_id": 1, "category_id": "as-0077824", "segmentation": [[[[207, 368], [211, 315], [222, 268], [238, 235], [244, 218], [244, 203], [252, 169], [297, 169], [307, 170], [315, 167], [334, 162], [370, 151], [392, 142], [411, 155], [438, 174], [456, 175], [466, 204], [463, 205], [436, 206], [354, 207], [344, 212], [344, 219], [353, 241], [362, 252], [401, 274], [388, 295], [356, 357], [348, 364], [289, 356], [283, 345], [273, 324], [261, 311], [244, 300], [232, 301], [223, 312], [216, 335], [216, 354], [219, 379], [207, 368]]]], "area": 28989.0, "bbox": [207, 142, 259, 237], "damage": null, "part": "Rear fender(L)", "year": 2016, "color": "Black", "level": 4, "repair": "Rear fender(L):coating,sheet_metal"}], "categories": {"id": "as-0077824", "supercategory_name": "Mid-size car"}}