{"info": {"name": "socar", "date_created": "03/08/2022"}, "images": {"id": 1, "width": 800, "height": 600, "file_name": "0001052_sc-197915.jpg"}, "annotations": [{"id": 2, "image_id": 1, "category_id": "sc-197915", "segmentation": [[[[158, 264], [156, 268], [140, 268], [133, 279], [137, 264], [144, 262], [158, 264]]]], "area": 125.5, "bbox": [133, 262, 25, 17], "damage": "Separated", "part": null, "year": 2016, "color": "White", "level": null, "repair": ["Rocker panel(R):coating", "Front bumper:coating,sheet_metal,exchange"]}, {"id": 3, "image_id": 1, "category_id": "sc-197915", "segmentation": [[[[162, 309], [187, 327], [209, 330], [230, 342], [219, 351], [195, 342], [173, 332], [167, 322], [162, 309]]]], "area": 848.0, "bbox": [162, 309, 68, 42], "damage": "Scratched", "part": null, "year": 2016, "color": "White", "level": null, "repair": ["Rocker panel(R):coating", "Front bumper:coating,sheet_metal,exchange"]}, {"id": 7, "image_id": 1, "category_id": "sc-197915", "segmentation": [[[[157, 266], [185, 273], [210, 283], [218, 290], [233, 298], [260, 313], [314, 334], [364, 355], [400, 369], [362, 388], [335, 394], [323, 395], [289, 391], [244, 378], [216, 368], [193, 356], [183, 348], [177, 340], [165, 319], [161, 305], [155, 281], [155, 273], [157, 266]]]], "area": 13941.0, "bbox": [155, 266, 245, 129], "damage": null, "part": "Head lights(R)", "year": 2016, "color": "White", "level": 4, "repair": ["Rocker panel(R):coating", "Front bumper:coating,sheet_metal,exchange"]}], "categories": {"id": "sc-197915", "supercategory_name": "Mid-size car"}}