{"info": {"name": "socar", "date_created": "03/08/2022"}, "images": {"id": 1, "width": 1280, "height": 960, "file_name": "0001312_sc-176476.jpg"}, "annotations": [{"id": 2, "image_id": 1, "category_id": "sc-176476", "segmentation": [[[[1004, 686], [983, 699], [914, 765], [892, 788], [892, 796], [899, 803], [939, 814], [938, 819], [908, 827], [876, 834], [846, 837], [846, 825], [847, 801], [830, 766], [831, 741], [847, 713], [872, 680], [897, 642], [960, 639], [981, 651], [1004, 686]]]], "area": 18256.0, "bbox": [830, 639, 174, 198], "damage": "Scratched", "part": null, "year": 2016, "color": "White", "level": null, "repair": ["Front bumper:coating,exchange"]}, {"id": 3, "image_id": 1, "category_id": "sc-176476", "segmentation": [[[[744, 689], [747, 680], [756, 690], [773, 719], [789, 757], [785, 800], [771, 834], [762, 837], [777, 785], [773, 749], [744, 689]]]], "area": 1822.5, "bbox": [744, 680, 45, 157], "damage": "Separated", "part": null, "year": 2016, "color": "White", "level": null, "repair": ["Front bumper:coating,exchange"]}, {"id": 6, "image_id": 1, "category_id": "sc-176476", "segmentation": [[[[1093, 732], [1081, 754], [1043, 776], [976, 809], [903, 832], [840, 847], [821, 847], [766, 836], [778, 811], [781, 763], [762, 701], [707, 630], [644, 577], [603, 557], [639, 538], [701, 526], [714, 542], [752, 575], [813, 612], [874, 634], [949, 632], [1028, 618], [1079, 598], [1117, 547], [1126, 526], [1121, 521], [1092, 520], [1131, 473], [1153, 427], [1161, 389], [1154, 355], [1168, 386], [1176, 430], [1180, 454], [1182, 486], [1173, 502], [1171, 522], [1171, 564], [1140, 630], [1104, 714], [1093, 732]]]], "area": 89023.5, "bbox": [603, 355, 579, 492], "damage": null, "part": "Front bumper", "year": 2016, "color": "White", "level": 4, "repair": "Front bumper:coating,exchange"}], "categories": {"id": "sc-176476", "supercategory_name": "Mid-size car"}}