{"info": {"name": "socar", "date_created": "03/08/2022"}, "images": {"id": 1, "width": 800, "height": 600, "file_name": "0000138_sc-1019190.jpg"}, "annotations": [{"id": 2, "image_id": 1, "category_id": "sc-1019190", "segmentation": [[[[277, 403], [295, 415], [362, 437], [473, 466], [590, 490], [600, 490], [604, 503], [600, 505], [499, 487], [399, 459], [295, 426], [277, 406], [277, 403]]]], "area": 4087.5, "bbox": [277, 403, 327, 102], "damage": "Separated", "part": null, "year": 2019, "color": "White", "level": null, "repair": ["Front bumper:repair,coating,exchange"]}], "categories": {"id": "sc-1019190", "supercategory_name": "Mid-size car"}}