{"info": {"name": "external", "date_created": "03/08/2022"}, "images": {"id": 1, "width": 800, "height": 600, "file_name": "0000408_as-0035224.jpg"}, "annotations": [{"id": 2, "image_id": 1, "category_id": "as-0035224", "segmentation": [[[[537, 175], [683, 153], [711, 166], [798, 163], [799, 185], [527, 205], [537, 175]]]], "area": 8244.5, "bbox": [527, 153, 272, 52], "damage": "Separated", "part": null, "year": 2019, "color": "White", "level": null, "repair": ["Front bumper:coating,exchange", "Head lights:exchange"]}, {"id": 3, "image_id": 1, "category_id": "as-0035224", "segmentation": [[[[60, 289], [189, 294], [178, 308], [57, 298], [60, 289]]]], "area": 1490.0, "bbox": [57, 289, 132, 19], "damage": "Separated", "part": null, "year": 2019, "color": "White", "level": null, "repair": ["Front bumper:coating,exchange", "Head lights:exchange"]}, {"id": 4, "image_id": 1, "category_id": "as-0035224", "segmentation": [[[[384, 92], [797, 89], [797, 103], [478, 110], [379, 105], [384, 92]]]], "area": 6747.0, "bbox": [379, 89, 418, 21], "damage": "Separated", "part": null, "year": 2019, "color": "White", "level": null, "repair": ["Front bumper:coating,exchange", "Head lights:exchange"]}, {"id": 5, "image_id": 1, "category_id": "as-0035224", "segmentation": [[[[64, 68], [201, 91], [192, 100], [77, 88], [64, 79], [64, 68]]]], "area": 1863.5, "bbox": [64, 68, 137, 32], "damage": "Separated", "part": null, "year": 2019, "color": "White", "level": null, "repair": ["Front bumper:coating,exchange", "Head lights:exchange"]}, {"id": 6, "image_id": 1, "category_id": "as-0035224", "segmentation": [[[[0, 25], [33, 0], [103, 0], [69, 26], [0, 40], [0, 25]]]], "area": 2306.5, "bbox": [0, 0, 103, 40], "damage": "Scratched", "part": null, "year": 2019, "color": "White", "level": null, "repair": ["Front bumper:coating,exchange", "Head lights:exchange"]}, {"id": 7, "image_id": 1, "category_id": "as-0035224", "segmentation": [[[[36, 103], [102, 79], [226, 99], [206, 115], [150, 117], [50, 115], [36, 103]]]], "area": 4720.0, "bbox": [36, 79, 190, 38], "damage": "Scratched", "part": null, "year": 2019, "color": "White", "level": null, "repair": ["Front bumper:coating,exchange", "Head lights:exchange"]}, {"id": 8, "image_id": 1, "category_id": "as-0035224", "segmentation": [[[[449, 128], [489, 149], [699, 147], [708, 167], [710, 175], [682, 169], [655, 164], [611, 167], [555, 174], [522, 178], [501, 165], [481, 162], [467, 163], [445, 148], [449, 128]]]], "area": 5590.0, "bbox": [445, 128, 265, 50], "damage": "Scratched", "part": null, "year": 2019, "color": "White", "level": null, "repair": ["Front bumper:coating,exchange", "Head lights:exchange"]}, {"id": 9, "image_id": 1, "category_id": "as-0035224", "segmentation": [[[[253, 313], [387, 250], [459, 226], [554, 202], [575, 208], [668, 197], [680, 226], [671, 257], [508, 279], [441, 299], [335, 316], [273, 321], [253, 313]]]], "area": 23040.0, "bbox": [253, 197, 427, 124], "damage": "Scratched", "part": null, "year": 2019, "color": "White", "level": null, "repair": ["Front bumper:coating,exchange", "Head lights:exchange"]}, {"id": 10, "image_id": 1, "category_id": "as-0035224", "segmentation": [[[[134, 170], [140, 172], [157, 180], [152, 231], [150, 242], [142, 242], [132, 252], [120, 261], [109, 250], [107, 207], [134, 170]]]], "area": 3144.5, "bbox": [107, 170, 50, 91], "damage": "Scratched", "part": null, "year": 2019, "color": "White", "level": null, "repair": ["Front bumper:coating,exchange", "Head lights:exchange"]}, {"id": 11, "image_id": 1, "category_id": "as-0035224", "segmentation": [[[[0, 277], [122, 289], [123, 301], [179, 314], [174, 333], [157, 369], [149, 388], [130, 400], [104, 410], [86, 415], [73, 417], [20, 382], [141, 383], [98, 326], [31, 313], [2, 316], [0, 277]]]], "area": 10675.0, "bbox": [0, 277, 179, 140], "damage": "Scratched", "part": null, "year": 2019, "color": "White", "level": null, "repair": ["Front bumper:coating,exchange", "Head lights:exchange"]}, {"id": 12, "image_id": 1, "category_id": "as-0035224", "segmentation": [[[[206, 368], [225, 347], [286, 398], [336, 428], [291, 453], [253, 464], [213, 454], [142, 442], [113, 427], [113, 418], [146, 421], [175, 417], [184, 394], [206, 368]]]], "area": 11823.0, "bbox": [113, 347, 223, 117], "damage": "Scratched", "part": null, "year": 2019, "color": "White", "level": null, "repair": ["Front bumper:coating,exchange", "Head lights:exchange"]}, {"id": 13, "image_id": 1, "category_id": "as-0035224", "segmentation": [[[[217, 90], [381, 95], [386, 113], [445, 134], [643, 160], [704, 173], [720, 184], [371, 238], [417, 302], [433, 336], [569, 317], [599, 386], [581, 408], [373, 427], [257, 357], [226, 377], [173, 409], [116, 450], [73, 451], [77, 404], [152, 320], [88, 271], [85, 251], [124, 261], [117, 134], [179, 87], [217, 90]]]], "area": 123607.5, "bbox": [73, 87, 647, 364], "damage": "Breakage", "part": null, "year": 2019, "color": "White", "level": null, "repair": ["Front bumper:coating,exchange", "Head lights:exchange"]}], "categories": {"id": "as-0035224", "supercategory_name": "Full-size car"}}