{"info": {"name": "socar", "date_created": "03/08/2022"}, "images": {"id": 1, "width": 800, "height": 600, "file_name": "0000424_sc-1007428.jpg"}, "annotations": [{"id": 2, "image_id": 1, "category_id": "sc-1007428", "segmentation": [[[[249, 359], [300, 369], [297, 378], [280, 384], [263, 383], [248, 370], [249, 359]]]], "area": 836.0, "bbox": [248, 359, 52, 25], "damage": "Scratched", "part": null, "year": 2019, "color": "White", "level": null, "repair": ["Rear bumper:coating,repair", "Front bumper:coating,sheet_metal", "Rear door(R):sheet_metal,coating"]}, {"id": 3, "image_id": 1, "category_id": "sc-1007428", "segmentation": [[[[407, 465], [415, 451], [430, 451], [435, 459], [407, 465]]]], "area": 232.0, "bbox": [407, 451, 28, 14], "damage": "Scratched", "part": null, "year": 2019, "color": "White", "level": null, "repair": ["Rear bumper:coating,repair", "Front bumper:coating,sheet_metal", "Rear door(R):sheet_metal,coating"]}], "categories": {"id": "sc-1007428", "supercategory_name": "Mid-size car"}}