{"info": {"name": "socar", "date_created": "03/08/2022"}, "images": {"id": 1, "width": 960, "height": 720, "file_name": "0000296_sc-189219.jpg"}, "annotations": [{"id": 2, "image_id": 1, "category_id": "sc-189219", "segmentation": [[[[360, 257], [387, 230], [397, 240], [471, 303], [546, 389], [546, 349], [530, 267], [538, 216], [666, 392], [666, 489], [674, 601], [660, 636], [568, 660], [484, 660], [465, 652], [438, 609], [419, 584], [449, 601], [465, 638], [565, 638], [606, 590], [571, 508], [508, 406], [360, 257]]]], "area": 49701.5, "bbox": [360, 216, 314, 444], "damage": "Scratched", "part": null, "year": 2017, "color": "White", "level": null, "repair": []}, {"id": 3, "image_id": 1, "category_id": "sc-189219", "segmentation": [[[[384, 0], [425, 0], [346, 72], [284, 154], [186, 332], [154, 373], [143, 365], [162, 311], [384, 0]]]], "area": 8060.0, "bbox": [143, 0, 282, 373], "damage": "Separated", "part": null, "year": 2017, "color": "White", "level": null, "repair": []}], "categories": {"id": "sc-189219", "supercategory_name": "CityCar"}}