{"info": {"name": "external", "date_created": "03/08/2022"}, "images": {"id": 1, "width": 800, "height": 600, "file_name": "0000287_as-0001700.jpg"}, "annotations": [{"id": 2, "image_id": 1, "category_id": "as-0001700", "segmentation": [[[[374, 345], [348, 329], [333, 292], [457, 285], [476, 315], [495, 321], [500, 335], [441, 347], [374, 345]]]], "area": 7564.5, "bbox": [333, 285, 167, 62], "damage": "Scratched", "part": null, "year": 2019, "color": "Black", "level": null, "repair": ["Front bumper:exchange,coating", "Front fender(L):coating,sheet_metal"]}, {"id": 3, "image_id": 1, "category_id": "as-0001700", "segmentation": [[[[471, 522], [473, 486], [572, 472], [608, 476], [602, 499], [549, 512], [471, 522]]]], "area": 4549.5, "bbox": [471, 472, 137, 50], "damage": "Scratched", "part": null, "year": 2019, "color": "Black", "level": null, "repair": ["Front bumper:exchange,coating", "Front fender(L):coating,sheet_metal"]}, {"id": 4, "image_id": 1, "category_id": "as-0001700", "segmentation": [[[[253, 331], [278, 336], [273, 375], [253, 331]]]], "area": 500.0, "bbox": [253, 331, 25, 44], "damage": "Separated", "part": null, "year": 2019, "color": "Black", "level": null, "repair": ["Front bumper:exchange,coating", "Front fender(L):coating,sheet_metal"]}, {"id": 5, "image_id": 1, "category_id": "as-0001700", "segmentation": [[[[395, 369], [405, 357], [479, 349], [574, 332], [634, 345], [573, 364], [470, 373], [395, 369]]]], "area": 4995.5, "bbox": [395, 332, 239, 41], "damage": "Breakage", "part": null, "year": 2019, "color": "Black", "level": null, "repair": ["Front bumper:exchange,coating", "Front fender(L):coating,sheet_metal"]}, {"id": 6, "image_id": 1, "category_id": "as-0001700", "segmentation": [[[[535, 208], [531, 158], [568, 102], [668, 62], [740, 84], [744, 150], [696, 204], [612, 244], [535, 208]]]], "area": 26712.0, "bbox": [531, 62, 213, 182], "damage": "Scratched", "part": null, "year": 2019, "color": "Black", "level": null, "repair": ["Front bumper:exchange,coating", "Front fender(L):coating,sheet_metal"]}, {"id": 7, "image_id": 1, "category_id": "as-0001700", "segmentation": [[[[216, 382], [230, 374], [333, 460], [387, 478], [480, 483], [588, 475], [698, 442], [800, 388], [799, 441], [584, 504], [477, 519], [403, 512], [336, 488], [216, 382]]]], "area": 17827.0, "bbox": [216, 374, 584, 145], "damage": "Separated", "part": null, "year": 2019, "color": "Black", "level": null, "repair": ["Front bumper:exchange,coating", "Front fender(L):coating,sheet_metal"]}], "categories": {"id": "as-0001700", "supercategory_name": "Full-size car"}}